usseg/__init__.py
usseg/example.py
usseg/General_functions.py
usseg/main.py
usseg/Organise_files.py
usseg/Refined_anon_2_html.py
usseg/Single_image_processing.py
usseg/visualisation_html.py
usseg-0.7.1.dist-info/LICENSE
usseg-0.7.1.dist-info/METADATA
usseg-0.7.1.dist-info/WHEEL
usseg-0.7.1.dist-info/RECORD
