Metadata-Version: 2.1
Name: usseg
Version: 0.7.1
Summary: Tools to segment doppler ultrasound signals from scan images.
License: GPL-v3-or-later
Author: Dale Kernot
Author-email: 874043@swansea.ac.uk
Requires-Python: >=3.10,<3.12
Classifier: License :: Other/Proprietary License
Classifier: Programming Language :: Python :: 3
Classifier: Programming Language :: Python :: 3.10
Classifier: Programming Language :: Python :: 3.11
Requires-Dist: matplotlib (>=3.7.1,<4.0.0)
Requires-Dist: nibabel (>=5.1.0,<6.0.0)
Requires-Dist: numpy (>=1.24.3,<2.0.0)
Requires-Dist: opencv-contrib-python (>=4.7.0.72,<5.0.0.0)
Requires-Dist: openpyxl (>=3.1.2,<4.0.0)
Requires-Dist: pandas (>=2.0.1,<3.0.0)
Requires-Dist: plotly (>=5.14.1,<6.0.0)
Requires-Dist: pytesseract (>=0.3.10,<0.4.0)
Requires-Dist: scikit-image (>=0.20.0,<0.21.0)
Requires-Dist: scikit-learn (>=1.2.2,<2.0.0)
Requires-Dist: scipy (>=1.10.1,<2.0.0)
Requires-Dist: super-image (>=0.1.7,<0.2.0)
Requires-Dist: toml (>=0.10.2,<0.11.0)
